{
    "currentPage": "home",
    "theme": false,
    "babies": [
        {
            "_id": "TSAQ7V-MX8VXV-SJ8QL2",
            "name": "Elizabeth Ruff",
            "birthday": "2023-12-04",
            "gender": "female",
            "active": true,
            "bm_data": [
                {
                    "_id": "SXFY41-YYUSYP-SBDL7J",
                    "cardType": "bm",
                    "type": "twoforone",
                    "note": "Nice this was 5 diapers! took about 30min",
                    "createdAt": "2024-01-06T19:41"
                },
                {
                    "_id": "KWQV7R-TT2DYE-I5FTV1",
                    "cardType": "bm",
                    "type": "poopy",
                    "note": "this was one of the biggest poop sessions!",
                    "createdAt": "2024-01-05T15:45"
                },
                {
                    "_id": "EXIB78-YDOUNN-M1FXP9",
                    "type": "poopy",
                    "cardType": "bm",
                    "note": "Took 3 diapers!",
                    "createdAt": "2024-01-02T05:43"
                },
                {
                    "_id": "UCZSQ5-DEMES6-UF1ERS",
                    "type": "potty",
                    "cardType": "bm",
                    "note": "Large potty",
                    "createdAt": "2024-01-01T21:12"
                },
                {
                    "_id": "16VHO2-QU7LB5-A2RCVE",
                    "cardType": "bm",
                    "type": "potty",
                    "note": "This was a test to see if the data was saved even without adding a note",
                    "createdAt": "2024-01-06T19:41"
                },
                {
                    "_id": "KJZ6P2-9A3RU7-23UDEQ",
                    "cardType": "bm",
                    "type": "poopy",
                    "note": "Unexpected mess, needed extra wipes!",
                    "createdAt": "2024-02-12T08:30"
                },
                {
                    "_id": "RYW9S4-GU5VZ2-WWL8HK",
                    "cardType": "bm",
                    "type": "twoforone",
                    "note": "Quick change, all good!",
                    "createdAt": "2024-03-25T17:20"
                },
                {
                    "_id": "LMPQXN-53U4R6-1BFW9V",
                    "type": "potty",
                    "cardType": "bm",
                    "note": "Small accident, but managed well!",
                    "createdAt": "2024-04-08T10:15"
                },
                {
                    "_id": "GQET8Z-HXK4N3-R5C6MJ",
                    "cardType": "bm",
                    "type": "poopy",
                    "note": "Surprise mess, took a while to clean up!",
                    "createdAt": "2024-05-19T14:55"
                },
                {
                    "_id": "WBY2K7-F9PJYD-5QRL6A",
                    "cardType": "bm",
                    "type": "twoforone",
                    "note": "Smooth change, very efficient!",
                    "createdAt": "2024-06-30T09:40"
                },
                {
                    "_id": "TUQDIJ-KFU4XE-U9X5TC",
                    "cardType": "bm",
                    "type": "potty",
                    "note": "large potty past midnight",
                    "createdAt": "2024-01-09T01:38"
                },
                {
                    "_id": "GSC4ED-YIVZTV-522IMN",
                    "cardType": "bm",
                    "type": "twoforone",
                    "note": "this was a big one after she ate!",
                    "createdAt": "2024-01-10T19:46"
                },
                {
                    "_id": "RL7ZTH-XEOFIB-5TWZVM",
                    "cardType": "bm",
                    "type": "poopy",
                    "note": "one diaper this time",
                    "createdAt": "2024-01-10T16:54"
                },
                {
                    "_id": "QRFGFB-EHAGWX-4VZW2Z",
                    "cardType": "bm",
                    "type": "poopy",
                    "note": "one diaper. so proud of her!",
                    "createdAt": "2024-01-10T13:15"
                },
                {
                    "_id": "YDR1IP-C8CVSE-AM5V21",
                    "cardType": "bm",
                    "type": "twoforone",
                    "note": "Largest poop known to man kind!",
                    "createdAt": "2024-01-11T07:33"
                },
                {
                    "_id": "8QN780-UFLKK4-RCK1D7",
                    "cardType": "bm",
                    "type": "potty",
                    "note": "large pooty just now!",
                    "createdAt": "2024-01-14T15:50"
                },
                {
                    "_id": "EFCHXA-F9ALMM-L3HB6K",
                    "cardType": "bm",
                    "type": "potty",
                    "note": "another one just now!",
                    "createdAt": "2024-01-14T15:59"
                },
                {
                    "_id": "8LNK58-BR2B3C-ONDF1W",
                    "cardType": "bm",
                    "type": "twoforone",
                    "note": "asdfsfsdfsd",
                    "createdAt": "2024-01-14T16:00"
                },
                {
                    "_id": "BY15BN-FGP10F-YWD3RU",
                    "cardType": "bm",
                    "type": "poopy",
                    "note": "another huge one!",
                    "createdAt": "2024-01-14T21:41"
                },
                {
                    "_id": "L1SD2I-8MBSQ3-56B6JV",
                    "cardType": "bm",
                    "type": "twoforone",
                    "note": "starting the day out with a bang!",
                    "createdAt": "2024-01-15T01:12"
                }
            ],
            "weight_data": [
                {
                    "_id": "6LAE8Y-J4UOL2-QPCFW7",
                    "pounds": "5",
                    "cardType": "weight",
                    "ounces": "8",
                    "createdAt": "2024-01-02T05:48"
                },
                {
                    "_id": "834X7X-CW2B7N-S1IM7O",
                    "pounds": "4",
                    "cardType": "weight",
                    "ounces": "1",
                    "createdAt": "2024-01-02T05:46"
                },
                {
                    "_id": "WWWVSM-5271DV-1X6YZF",
                    "pounds": "5",
                    "cardType": "weight",
                    "ounces": "1",
                    "createdAt": "2023-12-22T13:36"
                },
                {
                    "_id": "HV7HLP-9WVAU5-8UFDMC",
                    "pounds": "4",
                    "cardType": "weight",
                    "ounces": "9",
                    "createdAt": "2023-12-15T13:36"
                },
                {
                    "_id": "F6UG3D-M5QOIS-THV8B0",
                    "pounds": "4",
                    "cardType": "weight",
                    "ounces": "5",
                    "createdAt": "2023-12-12T11:34"
                },
                {
                    "_id": "2S2UH5-4VAF5O-O4PLCI",
                    "pounds": "4",
                    "cardType": "weight",
                    "ounces": "9",
                    "createdAt": "2023-12-04T07:31"
                },
                {
                    "_id": "6LAE8Y-J4UOL2-QPCFW7",
                    "pounds": "5",
                    "cardType": "weight",
                    "ounces": "8",
                    "createdAt": "2024-01-02T05:48"
                },
                {
                    "_id": "9ZRW3X-SF2VYQ-LMN6P5",
                    "pounds": "6",
                    "cardType": "weight",
                    "ounces": "3",
                    "createdAt": "2024-02-15T12:20"
                },
                {
                    "_id": "1QYHU7-PLB9ZA-FG3D2R",
                    "pounds": "4",
                    "cardType": "weight",
                    "ounces": "12",
                    "createdAt": "2024-03-28T08:05"
                },
                {
                    "_id": "5IOEK9-NJF4B6-Q2P7RZ",
                    "pounds": "7",
                    "cardType": "weight",
                    "ounces": "6",
                    "createdAt": "2024-05-10T17:30"
                },
                {
                    "_id": "8JRYD5-XYM9VU-KPAQ2T",
                    "pounds": "5",
                    "cardType": "weight",
                    "ounces": "10",
                    "createdAt": "2024-06-22T09:55"
                }
            ],
            "feed_data": [
                {
                    "_id": "B0XN47-H9VENP-8K0Z1P",
                    "cardType": "feed",
                    "ounces": "120",
                    "hours": "1",
                    "minutes": "2",
                    "createdAt": "2024-01-01T09:15"
                },
                {
                    "_id": "3WXBAS-NZ3WQT-VWLW4A",
                    "cardType": "feed",
                    "ounces": "75",
                    "hours": "0",
                    "minutes": "45",
                    "createdAt": "2024-01-01T06:15"
                },
                {
                    "_id": "5AHZS3-DVAK48-VOTA47",
                    "cardType": "feed",
                    "ounces": "90",
                    "hours": "1",
                    "minutes": "15",
                    "createdAt": "2024-01-01T03:10"
                },
                {
                    "_id": "B0XN47-H9VENP-8K0Z1P",
                    "cardType": "feed",
                    "ounces": "120",
                    "hours": "1",
                    "minutes": "2",
                    "createdAt": "2024-01-01T09:15"
                },
                {
                    "_id": "S6VY3R-2IHMN9-5JFQWK",
                    "cardType": "feed",
                    "ounces": "90",
                    "hours": "0",
                    "minutes": "45",
                    "createdAt": "2024-02-14T14:30"
                },
                {
                    "_id": "4PLK9J-W7RNE8-3ZA0DQ",
                    "cardType": "feed",
                    "ounces": "80",
                    "hours": "1",
                    "minutes": "20",
                    "createdAt": "2024-03-27T10:00"
                },
                {
                    "_id": "Q9P8ZM-TK7R63-HN24X1",
                    "cardType": "feed",
                    "ounces": "100",
                    "hours": "1",
                    "minutes": "10",
                    "createdAt": "2024-05-09T18:45"
                },
                {
                    "_id": "T8W5R7-J3F6NK-0QL24P",
                    "cardType": "feed",
                    "ounces": "110",
                    "hours": "1",
                    "minutes": "0",
                    "createdAt": "2024-06-21T11:20"
                }
            ],
            "achievements": [
                {
                    "achievement": "Cluster Feeding!",
                    "completed": false,
                    "achieved_at": ""
                },
                {
                    "achievement": "Most Active Poops!",
                    "completed": false,
                    "achieved_at": ""
                },
                {
                    "achievement": "First Recorded Poop!",
                    "completed": false,
                    "achieved_at": ""
                },
                {
                    "achievement": "First Recorded Weight!",
                    "completed": false,
                    "achieved_at": ""
                },
                {
                    "achievement": "First Recorded Feeding!",
                    "completed": false,
                    "achieved_at": ""
                }
            ],
            "milestones": [
                {
                    "milestone": "4-6 Month Doubled Birth Weight",
                    "completed": false,
                    "achieved_at": "",
                    "badge": ""
                }
            ]
        }
    ],
    "currentFilter": "most_recent",
    "currentData": "bm_data"
}